[
    {
        "avg_equil_alat": 5.246870040893555,
        "avg_good_alat": 5.24,
        "results": [
            {
                "spec": "Ar",
                "spec_equil_alat": 5.246870040893555,
                "spec_good_alat": 5.24,
                "spec_valid_alats": [
                    2.55,
                    2.56,
                    2.57,
                    2.58,
                    2.59,
                    2.6,
                    2.61,
                    2.62,
                    2.63,
                    2.64,
                    2.65,
                    2.66,
                    2.67,
                    2.68,
                    2.69,
                    2.7,
                    2.71,
                    2.72,
                    2.73,
                    2.74,
                    2.75,
                    2.76,
                    2.77,
                    2.7800000000000002,
                    2.79,
                    2.8,
                    2.81,
                    2.82,
                    2.83,
                    2.84,
                    2.85,
                    2.86,
                    2.87,
                    2.88,
                    2.89,
                    2.9,
                    2.91,
                    2.92,
                    2.93,
                    2.94,
                    2.95,
                    2.96,
                    2.97,
                    2.98,
                    2.99,
                    3.0,
                    3.01,
                    3.02,
                    3.0300000000000002,
                    3.04,
                    3.05,
                    3.06,
                    3.0700000000000003,
                    3.08,
                    3.09,
                    3.1,
                    3.11,
                    3.12,
                    3.13,
                    3.14,
                    3.15,
                    3.16,
                    3.17,
                    3.18,
                    3.19,
                    3.2,
                    3.21,
                    3.2199999999999998,
                    3.23,
                    3.24,
                    3.25,
                    3.26,
                    3.27,
                    3.2800000000000002,
                    3.29,
                    3.3,
                    3.31,
                    3.3200000000000003,
                    3.33,
                    3.34,
                    3.35,
                    3.36,
                    3.37,
                    3.38,
                    3.39,
                    3.4,
                    3.41,
                    3.42,
                    3.43,
                    3.44,
                    3.45,
                    3.46,
                    3.4699999999999998,
                    3.48,
                    3.49,
                    3.5,
                    3.51,
                    3.52,
                    3.5300000000000002,
                    3.54,
                    3.55,
                    3.56,
                    3.5700000000000003,
                    3.58,
                    3.59,
                    3.6,
                    3.6100000000000003,
                    3.62,
                    3.63,
                    3.64,
                    3.6500000000000004,
                    3.66,
                    3.67,
                    3.6799999999999997,
                    3.69,
                    3.7,
                    3.71,
                    3.7199999999999998,
                    3.73,
                    3.74,
                    3.75,
                    3.76,
                    3.77,
                    3.7800000000000002,
                    3.79,
                    3.8,
                    3.81,
                    3.8200000000000003,
                    3.83,
                    3.84,
                    3.85,
                    3.8600000000000003,
                    3.87,
                    3.88,
                    3.89,
                    3.9000000000000004,
                    3.91,
                    3.92,
                    3.9299999999999997,
                    3.94,
                    3.95,
                    3.96,
                    3.9699999999999998,
                    3.98,
                    3.99,
                    4.0,
                    4.01,
                    4.02,
                    4.03,
                    4.04,
                    4.05,
                    4.0600000000000005,
                    4.07,
                    4.08,
                    4.09,
                    4.1,
                    4.11,
                    4.12,
                    4.13,
                    4.140000000000001,
                    4.15,
                    4.16,
                    4.17,
                    4.18,
                    4.1899999999999995,
                    4.2,
                    4.21,
                    4.22,
                    4.23,
                    4.24,
                    4.25,
                    4.26,
                    4.27,
                    4.28,
                    4.29,
                    4.3,
                    4.3100000000000005,
                    4.32,
                    4.33,
                    4.34,
                    4.35,
                    4.36,
                    4.37,
                    4.38,
                    4.390000000000001,
                    4.4,
                    4.41,
                    4.42,
                    4.43,
                    4.4399999999999995,
                    4.45,
                    4.46,
                    4.47,
                    4.48,
                    4.49,
                    4.5,
                    4.51,
                    4.52,
                    4.53,
                    4.54,
                    4.55,
                    4.5600000000000005,
                    4.57,
                    4.58,
                    4.83,
                    4.84,
                    4.85,
                    4.859999999999999,
                    4.87,
                    4.88,
                    4.890000000000001,
                    4.9,
                    4.91,
                    4.92,
                    4.93,
                    4.9399999999999995,
                    4.95,
                    4.96,
                    4.970000000000001,
                    4.98,
                    4.99,
                    5.0,
                    5.01,
                    5.02,
                    5.03,
                    5.04,
                    5.050000000000001,
                    5.0600000000000005,
                    5.07,
                    5.08,
                    5.09,
                    5.1,
                    5.109999999999999,
                    5.12,
                    5.13,
                    5.140000000000001,
                    5.15,
                    5.16,
                    5.17,
                    5.18,
                    5.1899999999999995,
                    5.2,
                    5.21,
                    5.220000000000001,
                    5.23,
                    5.24,
                    5.25,
                    5.26,
                    5.27,
                    5.28,
                    5.29,
                    5.300000000000001,
                    5.3100000000000005,
                    5.32,
                    5.33,
                    5.34,
                    5.35,
                    5.359999999999999,
                    5.37,
                    5.38,
                    5.390000000000001,
                    5.4,
                    5.41,
                    5.42,
                    5.43,
                    5.4399999999999995,
                    5.45,
                    5.46,
                    5.470000000000001,
                    5.48,
                    5.49,
                    5.5,
                    5.51,
                    5.52,
                    5.53,
                    5.54,
                    5.550000000000001,
                    5.5600000000000005,
                    5.57,
                    5.58,
                    5.59,
                    5.6,
                    5.609999999999999,
                    5.62,
                    5.63,
                    5.640000000000001,
                    5.65,
                    5.66,
                    5.67,
                    5.68,
                    5.6899999999999995,
                    5.7,
                    5.71,
                    5.720000000000001,
                    5.73,
                    5.74,
                    5.75,
                    5.76,
                    5.77,
                    5.78,
                    5.79,
                    5.800000000000001,
                    5.8100000000000005,
                    5.82,
                    5.83,
                    5.84,
                    5.85,
                    5.859999999999999,
                    5.87,
                    5.88,
                    5.890000000000001,
                    5.9,
                    5.91,
                    5.92,
                    5.93,
                    5.9399999999999995,
                    5.95,
                    5.96,
                    5.970000000000001,
                    5.98,
                    5.99,
                    6.0,
                    6.01,
                    6.02,
                    6.03,
                    6.04,
                    6.050000000000001,
                    6.0600000000000005,
                    6.07,
                    6.08,
                    6.09,
                    6.1,
                    6.109999999999999,
                    6.12,
                    6.13,
                    6.140000000000001,
                    6.15,
                    6.16,
                    6.17,
                    6.18,
                    6.1899999999999995,
                    6.2,
                    6.21,
                    6.220000000000001,
                    6.23,
                    6.24,
                    6.25
                ],
                "spec_valid_energy": [
                    1957.525785878027,
                    1866.5055141989533,
                    1780.0201066979384,
                    1697.8272747042893,
                    1619.7000635430754,
                    1545.4225102938253,
                    1474.7931413088127,
                    1407.6185644331465,
                    1343.719424951237,
                    1282.9240746317232,
                    1225.0734065090662,
                    1170.0118165351375,
                    1117.5975452311764,
                    1067.6936555289103,
                    1020.1725457717417,
                    974.9117359389664,
                    931.796893232367,
                    890.7190777308548,
                    851.5769833520883,
                    814.2704539733795,
                    778.708840909339,
                    744.8049721497952,
                    712.4763150280208,
                    681.6458750579326,
                    652.2372807568162,
                    624.1820600889372,
                    597.4128232789294,
                    571.8677853448521,
                    547.4858317274495,
                    524.2110988347819,
                    501.99062927906243,
                    480.77212595137445,
                    460.50897278891017,
                    441.153474866535,
                    422.66313710856116,
                    404.9967170531799,
                    388.11506542379914,
                    371.9824287676484,
                    356.560652744915,
                    341.8176611628948,
                    327.7219247086543,
                    314.2425599649494,
                    301.35113954047324,
                    289.02104315464203,
                    277.2248875279055,
                    265.9386977246102,
                    255.1396956117913,
                    244.8041453027202,
                    234.9119966977252,
                    225.4420900010827,
                    216.3756864153538,
                    207.69459712621588,
                    199.3813910805961,
                    191.41921905046812,
                    183.79249429709103,
                    176.48723981029593,
                    169.48702863383704,
                    162.77929937247973,
                    156.35130079912645,
                    150.1901882359929,
                    144.28440998404966,
                    138.6236703254493,
                    133.19535733615635,
                    127.99021843694287,
                    122.99851640364108,
                    118.21096539399682,
                    113.61870875545678,
                    109.21329798712848,
                    104.98784832118181,
                    100.9322960927335,
                    97.04049923004867,
                    93.30545238845757,
                    89.72070200346532,
                    86.27939233048879,
                    82.97566530927327,
                    79.8048841284589,
                    76.75909807169953,
                    73.8342024566388,
                    71.02512331478216,
                    68.32748566543093,
                    65.73570219328677,
                    63.245826896436554,
                    60.853627630692905,
                    58.55553208265428,
                    56.34671687101961,
                    54.22396523097402,
                    52.18373997234021,
                    50.2226579682516,
                    48.33771648451013,
                    46.52534862403549,
                    44.78282972833095,
                    43.10732521495995,
                    41.49659218309036,
                    39.947086358062286,
                    38.45680030522343,
                    37.023354486004195,
                    35.64447054779648,
                    34.31819985104875,
                    33.04198286755382,
                    31.81405541965327,
                    30.632500457144495,
                    29.496661125133034,
                    28.4023986050405,
                    27.349226496183906,
                    26.33552883798254,
                    25.359756816041493,
                    24.420779202199068,
                    23.516460156848073,
                    22.64579445529808,
                    21.80747368663901,
                    21.000243133428135,
                    20.223371564584003,
                    19.474752855389717,
                    18.753759743999968,
                    18.059330026449413,
                    17.390444560146896,
                    16.74612541885454,
                    16.125901276295643,
                    15.527929680174406,
                    14.951820845525628,
                    14.396744869492036,
                    13.861905016089281,
                    13.347479477168745,
                    12.85083252052586,
                    12.372217061540066,
                    11.91095563534488,
                    11.466397539360415,
                    11.03791771733856,
                    10.624974497393966,
                    10.226872439752322,
                    9.843116945400968,
                    9.473175332289063,
                    9.116535677707901,
                    8.772705964984011,
                    8.442156009660293,
                    8.122531299224605,
                    7.814352185091261,
                    7.517198451717437,
                    7.230666045642617,
                    6.954366420416815,
                    6.687925909521106,
                    6.430985126035365,
                    6.18319838783861,
                    5.944233167207808,
                    5.713769563718153,
                    5.491499799410081,
                    5.277127735230125,
                    5.070604763085044,
                    4.871180444146215,
                    4.678830765820513,
                    4.493301701263855,
                    4.314348732340789,
                    4.141736475354769,
                    3.9752383222960783,
                    3.815109609588786,
                    3.6601863512318467,
                    3.5107467747157326,
                    3.3665960723337625,
                    3.227546628491345,
                    3.093417740880914,
                    2.9640353530330876,
                    2.8392317977624772,
                    2.7197858550207243,
                    2.6036478846616475,
                    2.491621891916478,
                    2.3835633988808853,
                    2.2793331819914218,
                    2.178797071716046,
                    2.0818257602762613,
                    1.988294617063076,
                    1.898318400231663,
                    1.8113082427606262,
                    1.7273907411560017,
                    1.64645826948715,
                    1.5684070606524052,
                    1.4931370616350408,
                    1.4205517944644692,
                    1.3505582226469441,
                    1.2838934910384605,
                    1.2188059653804395,
                    1.156050597903523,
                    1.0955468806783504,
                    1.037217153926732,
                    0.9809865008441689,
                    0.9267826464993781,
                    0.8745358606450635,
                    0.8241788642808172,
                    0.7757254130684572,
                    0.7289544585084928,
                    0.6838852992859158,
                    0.6404595965717814,
                    0.5986210467815408,
                    0.558315307671829,
                    0.5194899272505096,
                    0.4820942753873805,
                    0.4460794780180922,
                    0.41139835383776785,
                    0.378474309193682,
                    0.3463192798027664,
                    0.31536603316790124,
                    0.2855735707233639,
                    0.2569023041896164,
                    0.22931400526620493,
                    0.20277175720268004,
                    -0.2061596842666921,
                    -0.21486624787121658,
                    -0.22340318612722132,
                    -0.2315450952905882,
                    -0.23930562169553957,
                    -0.24669795752715643,
                    -0.2537348562354219,
                    -0.260428647405834,
                    -0.2667912511066595,
                    -0.2728341917320128,
                    -0.2785686113593373,
                    -0.2840052826390069,
                    -0.28915462123330704,
                    -0.2940266978210431,
                    -0.2979251956038434,
                    -0.30228010089488877,
                    -0.3063858820728382,
                    -0.31025134366559487,
                    -0.3138849992271018,
                    -0.3172950810492853,
                    -0.3204895495387434,
                    -0.32347610227015217,
                    -0.32626218272807267,
                    -0.3288549887482947,
                    -0.33126148066956274,
                    -0.33348838920592255,
                    -0.33554222304981624,
                    -0.3374144593302327,
                    -0.33886275954132083,
                    -0.3404377249209695,
                    -0.34186352696089056,
                    -0.3431456702348067,
                    -0.3442894777580461,
                    -0.34530009695525943,
                    -0.34618250542632273,
                    -0.3469415165175831,
                    -0.3475817847051571,
                    -0.34810781079703795,
                    -0.34852394696023997,
                    -0.3488344015791143,
                    -0.3490432439507851,
                    -0.3491544088233006,
                    -0.34869872053114415,
                    -0.34863118723513575,
                    -0.3484769455632242,
                    -0.3482394355610901,
                    -0.34792198322412554,
                    -0.3475278042006246,
                    -0.34706000737212617,
                    -0.34652159831516377,
                    -0.3459154826483752,
                    -0.3452444692690078,
                    -0.3445112734825459,
                    -0.343718520029226,
                    -0.3428687460107449,
                    -0.3419644037208434,
                    -0.341007863382774,
                    -0.34000141579703097,
                    -0.33882882301878714,
                    -0.33773043345543347,
                    -0.33658854095837576,
                    -0.3354051436668666,
                    -0.3341821722873994,
                    -0.3329214922629568,
                    -0.33162490587155086,
                    -0.3302941542565614,
                    -0.3289309193911619,
                    -0.32753682597897565,
                    -0.3261134432930704,
                    -0.32466228695554167,
                    -0.3231848206594053,
                    -0.32168245783493665,
                    -0.3201565632621774,
                    -0.3186084546314705,
                    -0.3170394040536948,
                    -0.31545063952193503,
                    -0.31337084718816804,
                    -0.311751208629867,
                    -0.31011522672351016,
                    -0.30846396757713346,
                    -0.30679845980044906,
                    -0.30511969570701497,
                    -0.3034286324779929,
                    -0.3017261932887174,
                    -0.3000132683992929,
                    -0.29829071621044007,
                    -0.29655936428567153,
                    -0.2948200103409012,
                    -0.2930734232026269,
                    -0.29132034373557664,
                    -0.289561485740953,
                    -0.2877975368261062,
                    -0.2860291592466794,
                    -0.2842569907220035,
                    -0.2824816452246952,
                    -0.2807037137452539,
                    -0.2789237650324811,
                    -0.27714234631045737,
                    -0.27535998397292816,
                    -0.2735771842557164,
                    -0.27179443388792474,
                    -0.2700122007226268,
                    -0.26823093434764156,
                    -0.26645106667711665,
                    -0.26467301252444264,
                    -0.2628971701571475,
                    -0.26112392183436817,
                    -0.2593536343273859,
                    -0.2575866594238257,
                    -0.2558233344160051,
                    -0.25406398257398555,
                    -0.25230891360372204,
                    -0.2505584240908867,
                    -0.2488127979307402,
                    -0.24707230674457958,
                    -0.24533721028302932,
                    -0.243607756816833,
                    -0.24188418351529453,
                    -0.23946176359993004,
                    -0.2377576157226274,
                    -0.23605991565501935,
                    -0.23436886078026484,
                    -0.2326846390862231,
                    -0.23100742947846167,
                    -0.22933740208345188,
                    -0.22767471854231033,
                    -0.226019532295328,
                    -0.2243719888576361,
                    -0.22273222608621865,
                    -0.22110037443860955,
                    -0.2194765572234639,
                    -0.21786089084334131,
                    -0.2162534850298562,
                    -0.21465444307148357,
                    -0.2130638620342597,
                    -0.21148183297556414,
                    -0.2099084411511902,
                    -0.20834376621599063,
                    -0.20678788241817772,
                    -0.2052408587875855,
                    -0.20370275931801726,
                    -0.20217364314388014,
                    -0.20041735822644385
                ],
                "spec_min_indices": [
                    245
                ],
                "spec_min_index": 245
            }
        ]
    }
]