{
    "model": "Morse_Shifted_Jelinek_1972_Ar__MO_831902330215_004",
    "species_list": [
        "Ar"
    ],
    "species_label": "Ar",
    "ncells_per_side": 2,
    "method": "coarse_scan_plus_nelder_mead_no_led",
    "mono_species_equilibrium_alats": {
        "Ar": 5.25354736328125
    },
    "approx_mixed_equilibrium_alat": 5.25354736328125,
    "mono_species_results": [
        {
            "ok": true,
            "status": "success",
            "configuration_type": "mono_species_fcc",
            "species_list": [
                "Ar"
            ],
            "species_label": "Ar",
            "good_alat": 5.25354736328125,
            "good_energy_per_atom": -0.09280316023629706,
            "good_energy_total": -2.969701127561506,
            "good_ncells": 2,
            "bounds": {
                "a_min": 1.5,
                "a_max": 12.0,
                "min_scan_alat_for_plateau": 6.5,
                "coarse_del_a": 0.1
            },
            "coarse_scan": {
                "alats": [
                    1.5,
                    1.6,
                    1.7,
                    1.8,
                    1.9,
                    2.0,
                    2.1,
                    2.2,
                    2.3,
                    2.4,
                    2.5,
                    2.6,
                    2.7,
                    2.8,
                    2.9,
                    3.0,
                    3.1,
                    3.2,
                    3.3,
                    3.4,
                    3.5,
                    3.6,
                    3.7,
                    3.8,
                    3.9,
                    4.0,
                    4.1,
                    4.2,
                    4.3,
                    4.4,
                    4.5,
                    4.6,
                    4.7,
                    4.8,
                    4.9,
                    5.0,
                    5.1,
                    5.2,
                    5.3,
                    5.4,
                    5.5,
                    5.6,
                    5.7,
                    5.8,
                    5.9,
                    6.0,
                    6.1,
                    6.2,
                    6.3,
                    6.4,
                    6.5,
                    6.6,
                    6.7,
                    6.8,
                    6.9,
                    7.0,
                    7.1,
                    7.2,
                    7.3,
                    7.4,
                    7.5,
                    7.6,
                    7.7,
                    7.8,
                    7.9,
                    8.0,
                    8.1,
                    8.2,
                    8.3,
                    8.4,
                    8.5,
                    8.6,
                    8.7,
                    8.8,
                    8.9,
                    9.0,
                    9.1,
                    9.2,
                    9.3,
                    9.4,
                    9.5,
                    9.6,
                    9.7,
                    9.8,
                    9.9,
                    10.0,
                    10.1,
                    10.2,
                    10.3,
                    10.4,
                    10.5,
                    10.6,
                    10.7,
                    10.8,
                    10.9,
                    11.0,
                    11.1,
                    11.2,
                    11.3,
                    11.4,
                    11.5,
                    11.6,
                    11.7,
                    11.8,
                    11.9,
                    12.0
                ],
                "energies_per_atom": [
                    486.02979831615653,
                    371.22981506033545,
                    285.38133818505656,
                    220.53624252045756,
                    171.146265059054,
                    133.26571038592016,
                    104.04441195508718,
                    81.39521429458102,
                    63.76997242457455,
                    50.00977295031356,
                    39.238949544009714,
                    30.79030496677257,
                    24.1523055441361,
                    18.930646207204543,
                    14.819749811905554,
                    11.581975487689958,
                    9.031485374247053,
                    7.0229670750666475,
                    5.441765572430094,
                    4.198301303842928,
                    3.2216739712894706,
                    2.4558517257972587,
                    1.8565874073571873,
                    1.3888777033859332,
                    1.024936835718084,
                    0.7428561671911494,
                    0.5252941950509864,
                    0.3584469655877889,
                    0.2314149529719729,
                    0.13546227502030175,
                    0.06376347358978095,
                    0.011036708771188671,
                    -0.026992435425755388,
                    -0.053720529326029734,
                    -0.07176326264641399,
                    -0.08319999800039436,
                    -0.08966015124771497,
                    -0.09245564037796285,
                    -0.09256933736191274,
                    -0.09071725890642389,
                    -0.08749280092229128,
                    -0.08335017168105638,
                    -0.07863432299602059,
                    -0.07361951006534993,
                    -0.06850324958675735,
                    -0.06339989790795537,
                    -0.058411427673759106,
                    -0.053608653774456866,
                    -0.04903856197188737,
                    -0.04473006164229408,
                    -0.040698488751617024,
                    -0.03694911882305597,
                    -0.03351138040706904,
                    -0.03037533444127543,
                    -0.027490903537183756,
                    -0.024846649118529407,
                    -0.022429407842940573,
                    -0.02022504757014277,
                    -0.018219030678499403,
                    -0.016396827312415353,
                    -0.01474421225559142,
                    -0.013247472044387922,
                    -0.01189354329879216,
                    -0.0106700987653731,
                    -0.009565594004804888,
                    -0.008569284830183124,
                    -0.0076712233627484385,
                    -0.0068693239393092425,
                    -0.0061536235477273864,
                    -0.005509056777468575,
                    -0.004928838052236602,
                    -0.0044067709593905435,
                    -0.003937209472568864,
                    -0.003515018830914989,
                    -0.0031355369655176727,
                    -0.0027945371036780502,
                    -0.002488191981465603,
                    -0.0022130399420625894,
                    -0.001965953081542495,
                    -0.0017441075169675733,
                    -0.001544955787653262,
                    -0.001366201354085604,
                    -0.001205775126293219,
                    -0.0010618139313097275,
                    -0.0009326408152271075,
                    -0.0008167470672774245,
                    -0.0007127758498572103,
                    -0.0006195073182283224,
                    -0.0005358451158604617,
                    -0.0004608041353049579,
                    -0.0003934994395536465,
                    -0.00033313624461951024,
                    -0.00027900087025886747,
                    -0.00023045257210075698,
                    -0.0001869161747836586,
                    -0.0001478754318968811,
                    -0.00011286704449678575,
                    -8.147527565755665e-05,
                    -5.332710388617035e-05,
                    -2.8087863261879512e-05,
                    -5.457322844342086e-06,
                    0.0,
                    0.0,
                    0.0,
                    0.0,
                    0.0
                ],
                "energy_total": [
                    15552.953546117009,
                    11879.354081930735,
                    9132.20282192181,
                    7057.159760654642,
                    5476.680481889728,
                    4264.502732349445,
                    3329.42118256279,
                    2604.6468574265928,
                    2040.6391175863855,
                    1600.312734410034,
                    1255.6463854083108,
                    985.2897589367223,
                    772.8737774123553,
                    605.7806786305454,
                    474.23199398097773,
                    370.62321560607865,
                    289.0075319759057,
                    224.73494640213272,
                    174.136498317763,
                    134.3456417229737,
                    103.09356708126306,
                    78.58725522551228,
                    59.410797035429994,
                    44.44408650834986,
                    32.797978742978685,
                    23.771397350116782,
                    16.809414241631565,
                    11.470302898809244,
                    7.405278495103133,
                    4.334792800649656,
                    2.0404311548729903,
                    0.3531746806780375,
                    -0.8637579336241724,
                    -1.7190569384329515,
                    -2.2964244046852476,
                    -2.6623999360126196,
                    -2.869124839926879,
                    -2.958580492094811,
                    -2.9622187955812076,
                    -2.9029522850055645,
                    -2.799769629513321,
                    -2.667205493793804,
                    -2.516298335872659,
                    -2.355824322091198,
                    -2.1921039867762353,
                    -2.028796733054572,
                    -1.8691656855602914,
                    -1.7154769207826197,
                    -1.5692339831003959,
                    -1.4313619725534106,
                    -1.3023516400517448,
                    -1.182371802337791,
                    -1.0723641730262092,
                    -0.9720107021208138,
                    -0.8797089131898802,
                    -0.795092771792941,
                    -0.7177410509740983,
                    -0.6472015222445686,
                    -0.5830089817119809,
                    -0.5246984739972913,
                    -0.4718147921789254,
                    -0.4239191054204135,
                    -0.38059338556134914,
                    -0.3414431604919392,
                    -0.3060990081537564,
                    -0.27421711456585995,
                    -0.24547914760795003,
                    -0.21981836605789576,
                    -0.19691595352727637,
                    -0.1762898168789944,
                    -0.15772281767157126,
                    -0.1410166707004974,
                    -0.12599070312220365,
                    -0.11248060258927965,
                    -0.10033718289656553,
                    -0.08942518731769761,
                    -0.0796221434068993,
                    -0.07081727814600286,
                    -0.06291049860935984,
                    -0.055811440542962346,
                    -0.049438585204904385,
                    -0.04371844333073933,
                    -0.03858480404138301,
                    -0.03397804580191128,
                    -0.02984450608726744,
                    -0.026135906152877583,
                    -0.02280882719543073,
                    -0.019824234183306318,
                    -0.017147043707534775,
                    -0.014745732329758654,
                    -0.012591982065716689,
                    -0.010660359827824328,
                    -0.008928027848283759,
                    -0.007374482307224223,
                    -0.005981317593077075,
                    -0.0047320138207001955,
                    -0.003611745423897144,
                    -0.002607208821041813,
                    -0.0017064673243574512,
                    -0.0008988116243801444,
                    -0.00017463433101894675,
                    0.0,
                    0.0,
                    0.0,
                    0.0,
                    0.0
                ],
                "ncells": [
                    2,
                    2,
                    2,
                    2,
                    2,
                    2,
                    2,
                    2,
                    2,
                    2,
                    2,
                    2,
                    2,
                    2,
                    2,
                    2,
                    2,
                    2,
                    2,
                    2,
                    2,
                    2,
                    2,
                    2,
                    2,
                    2,
                    2,
                    2,
                    2,
                    2,
                    2,
                    2,
                    2,
                    2,
                    2,
                    2,
                    2,
                    2,
                    2,
                    2,
                    2,
                    2,
                    2,
                    2,
                    2,
                    2,
                    2,
                    2,
                    2,
                    2,
                    2,
                    2,
                    2,
                    2,
                    2,
                    2,
                    2,
                    2,
                    2,
                    2,
                    2,
                    2,
                    2,
                    2,
                    2,
                    2,
                    2,
                    2,
                    2,
                    2,
                    2,
                    2,
                    2,
                    2,
                    2,
                    2,
                    2,
                    2,
                    2,
                    2,
                    2,
                    2,
                    2,
                    2,
                    2,
                    2,
                    2,
                    2,
                    2,
                    2,
                    2,
                    2,
                    2,
                    2,
                    2,
                    2,
                    2,
                    2,
                    2,
                    2,
                    2,
                    2,
                    2,
                    2,
                    2,
                    2
                ],
                "a_min": 1.5,
                "a_max": 12.0,
                "del_a": 0.1,
                "initial_use_safe": true,
                "safe_successes_before_direct": 10,
                "switched_to_direct": true,
                "switch_alat": 2.4,
                "early_stop_plateau": true,
                "plateau_stop_alat": null
            },
            "coarse_minima": [
                {
                    "index": 38,
                    "alat": 5.3,
                    "energy_per_atom": -0.09256933736191274
                }
            ],
            "nelder_mead_attempts": [
                {
                    "ok": true,
                    "status": "success",
                    "message": "Optimization terminated successfully.",
                    "start_alat": 5.3,
                    "good_alat": 5.25354736328125,
                    "good_energy_total": -2.969701127561506,
                    "good_energy_per_atom": -0.09280316023629706,
                    "good_ncells": 2,
                    "optimizer_x": 5.25354736328125,
                    "optimizer_fun": -0.09280316023629706,
                    "nfev": 26,
                    "nit": 13,
                    "evaluations": [
                        {
                            "alat": 5.3,
                            "energy_total": -2.9622187955812076,
                            "energy_per_atom": -0.09256933736191274,
                            "ncells": 2
                        },
                        {
                            "alat": 5.565,
                            "energy_total": -2.7161899346478195,
                            "energy_per_atom": -0.08488093545774436,
                            "ncells": 2
                        },
                        {
                            "alat": 5.034999999999999,
                            "energy_total": -2.750569742488627,
                            "energy_per_atom": -0.0859553044527696,
                            "ncells": 2
                        },
                        {
                            "alat": 5.167499999999999,
                            "energy_total": -2.939926596296568,
                            "energy_per_atom": -0.09187270613426775,
                            "ncells": 2
                        },
                        {
                            "alat": 5.432500000000001,
                            "energy_total": -2.8734504536512353,
                            "energy_per_atom": -0.0897953266766011,
                            "ncells": 2
                        },
                        {
                            "alat": 5.233749999999999,
                            "energy_total": -2.9682356033004322,
                            "energy_per_atom": -0.09275736260313851,
                            "ncells": 2
                        },
                        {
                            "alat": 5.167499999999998,
                            "energy_total": -2.939926596296568,
                            "energy_per_atom": -0.09187270613426775,
                            "ncells": 2
                        },
                        {
                            "alat": 5.266874999999999,
                            "energy_total": -2.969063466001878,
                            "energy_per_atom": -0.0927832333125587,
                            "ncells": 2
                        },
                        {
                            "alat": 5.299999999999999,
                            "energy_total": -2.9622187955812076,
                            "energy_per_atom": -0.09256933736191274,
                            "ncells": 2
                        },
                        {
                            "alat": 5.250312499999999,
                            "energy_total": -2.9696623888848372,
                            "energy_per_atom": -0.09280194965265116,
                            "ncells": 2
                        },
                        {
                            "alat": 5.233749999999999,
                            "energy_total": -2.9682356033004322,
                            "energy_per_atom": -0.09275736260313851,
                            "ncells": 2
                        },
                        {
                            "alat": 5.258593749999999,
                            "energy_total": -2.969609236937775,
                            "energy_per_atom": -0.09280028865430547,
                            "ncells": 2
                        },
                        {
                            "alat": 5.242031249999998,
                            "energy_total": -2.969209187971423,
                            "energy_per_atom": -0.09278778712410697,
                            "ncells": 2
                        },
                        {
                            "alat": 5.2544531249999995,
                            "energy_total": -2.9696982417588678,
                            "energy_per_atom": -0.09280307005496462,
                            "ncells": 2
                        },
                        {
                            "alat": 5.25859375,
                            "energy_total": -2.9696092369377585,
                            "energy_per_atom": -0.09280028865430495,
                            "ncells": 2
                        },
                        {
                            "alat": 5.252382812499999,
                            "energy_total": -2.969696029968217,
                            "energy_per_atom": -0.09280300093650679,
                            "ncells": 2
                        },
                        {
                            "alat": 5.2565234375,
                            "energy_total": -2.969669239412892,
                            "energy_per_atom": -0.09280216373165287,
                            "ncells": 2
                        },
                        {
                            "alat": 5.253417968749999,
                            "energy_total": -2.9697010510508752,
                            "energy_per_atom": -0.09280315784533985,
                            "ncells": 2
                        },
                        {
                            "alat": 5.252382812499999,
                            "energy_total": -2.969696029968217,
                            "energy_per_atom": -0.09280300093650679,
                            "ncells": 2
                        },
                        {
                            "alat": 5.253935546874999,
                            "energy_total": -2.969700623521403,
                            "energy_per_atom": -0.09280314448504384,
                            "ncells": 2
                        },
                        {
                            "alat": 5.252900390624999,
                            "energy_total": -2.9696995209878754,
                            "energy_per_atom": -0.0928031100308711,
                            "ncells": 2
                        },
                        {
                            "alat": 5.253676757812499,
                            "energy_total": -2.9697010817750846,
                            "energy_per_atom": -0.0928031588054714,
                            "ncells": 2
                        },
                        {
                            "alat": 5.253935546875,
                            "energy_total": -2.9697006235214007,
                            "energy_per_atom": -0.09280314448504377,
                            "ncells": 2
                        },
                        {
                            "alat": 5.25354736328125,
                            "energy_total": -2.969701127561506,
                            "energy_per_atom": -0.09280316023629706,
                            "ncells": 2
                        },
                        {
                            "alat": 5.25341796875,
                            "energy_total": -2.9697010510508752,
                            "energy_per_atom": -0.09280315784533985,
                            "ncells": 2
                        },
                        {
                            "alat": 5.253612060546875,
                            "energy_total": -2.9697011199521723,
                            "energy_per_atom": -0.09280315999850539,
                            "ncells": 2
                        }
                    ]
                }
            ],
            "selected_attempt_index": 0,
            "search_strategy": "coarse_scan_plus_nelder_mead_no_led",
            "all_alats": [
                5.3,
                5.565,
                5.034999999999999,
                5.167499999999999,
                5.432500000000001,
                5.233749999999999,
                5.167499999999998,
                5.266874999999999,
                5.299999999999999,
                5.250312499999999,
                5.233749999999999,
                5.258593749999999,
                5.242031249999998,
                5.2544531249999995,
                5.25859375,
                5.252382812499999,
                5.2565234375,
                5.253417968749999,
                5.252382812499999,
                5.253935546874999,
                5.252900390624999,
                5.253676757812499,
                5.253935546875,
                5.25354736328125,
                5.25341796875,
                5.253612060546875
            ],
            "all_energies_per_atom": [
                -0.09256933736191274,
                -0.08488093545774436,
                -0.0859553044527696,
                -0.09187270613426775,
                -0.0897953266766011,
                -0.09275736260313851,
                -0.09187270613426775,
                -0.0927832333125587,
                -0.09256933736191274,
                -0.09280194965265116,
                -0.09275736260313851,
                -0.09280028865430547,
                -0.09278778712410697,
                -0.09280307005496462,
                -0.09280028865430495,
                -0.09280300093650679,
                -0.09280216373165287,
                -0.09280315784533985,
                -0.09280300093650679,
                -0.09280314448504384,
                -0.0928031100308711,
                -0.0928031588054714,
                -0.09280314448504377,
                -0.09280316023629706,
                -0.09280315784533985,
                -0.09280315999850539
            ]
        }
    ],
    "mixed_species_result": null,
    "final_result": {
        "ok": true,
        "status": "success",
        "configuration_type": "mono_species_fcc",
        "species_list": [
            "Ar"
        ],
        "species_label": "Ar",
        "good_alat": 5.25354736328125,
        "good_energy_per_atom": -0.09280316023629706,
        "good_energy_total": -2.969701127561506,
        "good_ncells": 2,
        "bounds": {
            "a_min": 1.5,
            "a_max": 12.0,
            "min_scan_alat_for_plateau": 6.5,
            "coarse_del_a": 0.1
        },
        "coarse_scan": {
            "alats": [
                1.5,
                1.6,
                1.7,
                1.8,
                1.9,
                2.0,
                2.1,
                2.2,
                2.3,
                2.4,
                2.5,
                2.6,
                2.7,
                2.8,
                2.9,
                3.0,
                3.1,
                3.2,
                3.3,
                3.4,
                3.5,
                3.6,
                3.7,
                3.8,
                3.9,
                4.0,
                4.1,
                4.2,
                4.3,
                4.4,
                4.5,
                4.6,
                4.7,
                4.8,
                4.9,
                5.0,
                5.1,
                5.2,
                5.3,
                5.4,
                5.5,
                5.6,
                5.7,
                5.8,
                5.9,
                6.0,
                6.1,
                6.2,
                6.3,
                6.4,
                6.5,
                6.6,
                6.7,
                6.8,
                6.9,
                7.0,
                7.1,
                7.2,
                7.3,
                7.4,
                7.5,
                7.6,
                7.7,
                7.8,
                7.9,
                8.0,
                8.1,
                8.2,
                8.3,
                8.4,
                8.5,
                8.6,
                8.7,
                8.8,
                8.9,
                9.0,
                9.1,
                9.2,
                9.3,
                9.4,
                9.5,
                9.6,
                9.7,
                9.8,
                9.9,
                10.0,
                10.1,
                10.2,
                10.3,
                10.4,
                10.5,
                10.6,
                10.7,
                10.8,
                10.9,
                11.0,
                11.1,
                11.2,
                11.3,
                11.4,
                11.5,
                11.6,
                11.7,
                11.8,
                11.9,
                12.0
            ],
            "energies_per_atom": [
                486.02979831615653,
                371.22981506033545,
                285.38133818505656,
                220.53624252045756,
                171.146265059054,
                133.26571038592016,
                104.04441195508718,
                81.39521429458102,
                63.76997242457455,
                50.00977295031356,
                39.238949544009714,
                30.79030496677257,
                24.1523055441361,
                18.930646207204543,
                14.819749811905554,
                11.581975487689958,
                9.031485374247053,
                7.0229670750666475,
                5.441765572430094,
                4.198301303842928,
                3.2216739712894706,
                2.4558517257972587,
                1.8565874073571873,
                1.3888777033859332,
                1.024936835718084,
                0.7428561671911494,
                0.5252941950509864,
                0.3584469655877889,
                0.2314149529719729,
                0.13546227502030175,
                0.06376347358978095,
                0.011036708771188671,
                -0.026992435425755388,
                -0.053720529326029734,
                -0.07176326264641399,
                -0.08319999800039436,
                -0.08966015124771497,
                -0.09245564037796285,
                -0.09256933736191274,
                -0.09071725890642389,
                -0.08749280092229128,
                -0.08335017168105638,
                -0.07863432299602059,
                -0.07361951006534993,
                -0.06850324958675735,
                -0.06339989790795537,
                -0.058411427673759106,
                -0.053608653774456866,
                -0.04903856197188737,
                -0.04473006164229408,
                -0.040698488751617024,
                -0.03694911882305597,
                -0.03351138040706904,
                -0.03037533444127543,
                -0.027490903537183756,
                -0.024846649118529407,
                -0.022429407842940573,
                -0.02022504757014277,
                -0.018219030678499403,
                -0.016396827312415353,
                -0.01474421225559142,
                -0.013247472044387922,
                -0.01189354329879216,
                -0.0106700987653731,
                -0.009565594004804888,
                -0.008569284830183124,
                -0.0076712233627484385,
                -0.0068693239393092425,
                -0.0061536235477273864,
                -0.005509056777468575,
                -0.004928838052236602,
                -0.0044067709593905435,
                -0.003937209472568864,
                -0.003515018830914989,
                -0.0031355369655176727,
                -0.0027945371036780502,
                -0.002488191981465603,
                -0.0022130399420625894,
                -0.001965953081542495,
                -0.0017441075169675733,
                -0.001544955787653262,
                -0.001366201354085604,
                -0.001205775126293219,
                -0.0010618139313097275,
                -0.0009326408152271075,
                -0.0008167470672774245,
                -0.0007127758498572103,
                -0.0006195073182283224,
                -0.0005358451158604617,
                -0.0004608041353049579,
                -0.0003934994395536465,
                -0.00033313624461951024,
                -0.00027900087025886747,
                -0.00023045257210075698,
                -0.0001869161747836586,
                -0.0001478754318968811,
                -0.00011286704449678575,
                -8.147527565755665e-05,
                -5.332710388617035e-05,
                -2.8087863261879512e-05,
                -5.457322844342086e-06,
                0.0,
                0.0,
                0.0,
                0.0,
                0.0
            ],
            "energy_total": [
                15552.953546117009,
                11879.354081930735,
                9132.20282192181,
                7057.159760654642,
                5476.680481889728,
                4264.502732349445,
                3329.42118256279,
                2604.6468574265928,
                2040.6391175863855,
                1600.312734410034,
                1255.6463854083108,
                985.2897589367223,
                772.8737774123553,
                605.7806786305454,
                474.23199398097773,
                370.62321560607865,
                289.0075319759057,
                224.73494640213272,
                174.136498317763,
                134.3456417229737,
                103.09356708126306,
                78.58725522551228,
                59.410797035429994,
                44.44408650834986,
                32.797978742978685,
                23.771397350116782,
                16.809414241631565,
                11.470302898809244,
                7.405278495103133,
                4.334792800649656,
                2.0404311548729903,
                0.3531746806780375,
                -0.8637579336241724,
                -1.7190569384329515,
                -2.2964244046852476,
                -2.6623999360126196,
                -2.869124839926879,
                -2.958580492094811,
                -2.9622187955812076,
                -2.9029522850055645,
                -2.799769629513321,
                -2.667205493793804,
                -2.516298335872659,
                -2.355824322091198,
                -2.1921039867762353,
                -2.028796733054572,
                -1.8691656855602914,
                -1.7154769207826197,
                -1.5692339831003959,
                -1.4313619725534106,
                -1.3023516400517448,
                -1.182371802337791,
                -1.0723641730262092,
                -0.9720107021208138,
                -0.8797089131898802,
                -0.795092771792941,
                -0.7177410509740983,
                -0.6472015222445686,
                -0.5830089817119809,
                -0.5246984739972913,
                -0.4718147921789254,
                -0.4239191054204135,
                -0.38059338556134914,
                -0.3414431604919392,
                -0.3060990081537564,
                -0.27421711456585995,
                -0.24547914760795003,
                -0.21981836605789576,
                -0.19691595352727637,
                -0.1762898168789944,
                -0.15772281767157126,
                -0.1410166707004974,
                -0.12599070312220365,
                -0.11248060258927965,
                -0.10033718289656553,
                -0.08942518731769761,
                -0.0796221434068993,
                -0.07081727814600286,
                -0.06291049860935984,
                -0.055811440542962346,
                -0.049438585204904385,
                -0.04371844333073933,
                -0.03858480404138301,
                -0.03397804580191128,
                -0.02984450608726744,
                -0.026135906152877583,
                -0.02280882719543073,
                -0.019824234183306318,
                -0.017147043707534775,
                -0.014745732329758654,
                -0.012591982065716689,
                -0.010660359827824328,
                -0.008928027848283759,
                -0.007374482307224223,
                -0.005981317593077075,
                -0.0047320138207001955,
                -0.003611745423897144,
                -0.002607208821041813,
                -0.0017064673243574512,
                -0.0008988116243801444,
                -0.00017463433101894675,
                0.0,
                0.0,
                0.0,
                0.0,
                0.0
            ],
            "ncells": [
                2,
                2,
                2,
                2,
                2,
                2,
                2,
                2,
                2,
                2,
                2,
                2,
                2,
                2,
                2,
                2,
                2,
                2,
                2,
                2,
                2,
                2,
                2,
                2,
                2,
                2,
                2,
                2,
                2,
                2,
                2,
                2,
                2,
                2,
                2,
                2,
                2,
                2,
                2,
                2,
                2,
                2,
                2,
                2,
                2,
                2,
                2,
                2,
                2,
                2,
                2,
                2,
                2,
                2,
                2,
                2,
                2,
                2,
                2,
                2,
                2,
                2,
                2,
                2,
                2,
                2,
                2,
                2,
                2,
                2,
                2,
                2,
                2,
                2,
                2,
                2,
                2,
                2,
                2,
                2,
                2,
                2,
                2,
                2,
                2,
                2,
                2,
                2,
                2,
                2,
                2,
                2,
                2,
                2,
                2,
                2,
                2,
                2,
                2,
                2,
                2,
                2,
                2,
                2,
                2,
                2
            ],
            "a_min": 1.5,
            "a_max": 12.0,
            "del_a": 0.1,
            "initial_use_safe": true,
            "safe_successes_before_direct": 10,
            "switched_to_direct": true,
            "switch_alat": 2.4,
            "early_stop_plateau": true,
            "plateau_stop_alat": null
        },
        "coarse_minima": [
            {
                "index": 38,
                "alat": 5.3,
                "energy_per_atom": -0.09256933736191274
            }
        ],
        "nelder_mead_attempts": [
            {
                "ok": true,
                "status": "success",
                "message": "Optimization terminated successfully.",
                "start_alat": 5.3,
                "good_alat": 5.25354736328125,
                "good_energy_total": -2.969701127561506,
                "good_energy_per_atom": -0.09280316023629706,
                "good_ncells": 2,
                "optimizer_x": 5.25354736328125,
                "optimizer_fun": -0.09280316023629706,
                "nfev": 26,
                "nit": 13,
                "evaluations": [
                    {
                        "alat": 5.3,
                        "energy_total": -2.9622187955812076,
                        "energy_per_atom": -0.09256933736191274,
                        "ncells": 2
                    },
                    {
                        "alat": 5.565,
                        "energy_total": -2.7161899346478195,
                        "energy_per_atom": -0.08488093545774436,
                        "ncells": 2
                    },
                    {
                        "alat": 5.034999999999999,
                        "energy_total": -2.750569742488627,
                        "energy_per_atom": -0.0859553044527696,
                        "ncells": 2
                    },
                    {
                        "alat": 5.167499999999999,
                        "energy_total": -2.939926596296568,
                        "energy_per_atom": -0.09187270613426775,
                        "ncells": 2
                    },
                    {
                        "alat": 5.432500000000001,
                        "energy_total": -2.8734504536512353,
                        "energy_per_atom": -0.0897953266766011,
                        "ncells": 2
                    },
                    {
                        "alat": 5.233749999999999,
                        "energy_total": -2.9682356033004322,
                        "energy_per_atom": -0.09275736260313851,
                        "ncells": 2
                    },
                    {
                        "alat": 5.167499999999998,
                        "energy_total": -2.939926596296568,
                        "energy_per_atom": -0.09187270613426775,
                        "ncells": 2
                    },
                    {
                        "alat": 5.266874999999999,
                        "energy_total": -2.969063466001878,
                        "energy_per_atom": -0.0927832333125587,
                        "ncells": 2
                    },
                    {
                        "alat": 5.299999999999999,
                        "energy_total": -2.9622187955812076,
                        "energy_per_atom": -0.09256933736191274,
                        "ncells": 2
                    },
                    {
                        "alat": 5.250312499999999,
                        "energy_total": -2.9696623888848372,
                        "energy_per_atom": -0.09280194965265116,
                        "ncells": 2
                    },
                    {
                        "alat": 5.233749999999999,
                        "energy_total": -2.9682356033004322,
                        "energy_per_atom": -0.09275736260313851,
                        "ncells": 2
                    },
                    {
                        "alat": 5.258593749999999,
                        "energy_total": -2.969609236937775,
                        "energy_per_atom": -0.09280028865430547,
                        "ncells": 2
                    },
                    {
                        "alat": 5.242031249999998,
                        "energy_total": -2.969209187971423,
                        "energy_per_atom": -0.09278778712410697,
                        "ncells": 2
                    },
                    {
                        "alat": 5.2544531249999995,
                        "energy_total": -2.9696982417588678,
                        "energy_per_atom": -0.09280307005496462,
                        "ncells": 2
                    },
                    {
                        "alat": 5.25859375,
                        "energy_total": -2.9696092369377585,
                        "energy_per_atom": -0.09280028865430495,
                        "ncells": 2
                    },
                    {
                        "alat": 5.252382812499999,
                        "energy_total": -2.969696029968217,
                        "energy_per_atom": -0.09280300093650679,
                        "ncells": 2
                    },
                    {
                        "alat": 5.2565234375,
                        "energy_total": -2.969669239412892,
                        "energy_per_atom": -0.09280216373165287,
                        "ncells": 2
                    },
                    {
                        "alat": 5.253417968749999,
                        "energy_total": -2.9697010510508752,
                        "energy_per_atom": -0.09280315784533985,
                        "ncells": 2
                    },
                    {
                        "alat": 5.252382812499999,
                        "energy_total": -2.969696029968217,
                        "energy_per_atom": -0.09280300093650679,
                        "ncells": 2
                    },
                    {
                        "alat": 5.253935546874999,
                        "energy_total": -2.969700623521403,
                        "energy_per_atom": -0.09280314448504384,
                        "ncells": 2
                    },
                    {
                        "alat": 5.252900390624999,
                        "energy_total": -2.9696995209878754,
                        "energy_per_atom": -0.0928031100308711,
                        "ncells": 2
                    },
                    {
                        "alat": 5.253676757812499,
                        "energy_total": -2.9697010817750846,
                        "energy_per_atom": -0.0928031588054714,
                        "ncells": 2
                    },
                    {
                        "alat": 5.253935546875,
                        "energy_total": -2.9697006235214007,
                        "energy_per_atom": -0.09280314448504377,
                        "ncells": 2
                    },
                    {
                        "alat": 5.25354736328125,
                        "energy_total": -2.969701127561506,
                        "energy_per_atom": -0.09280316023629706,
                        "ncells": 2
                    },
                    {
                        "alat": 5.25341796875,
                        "energy_total": -2.9697010510508752,
                        "energy_per_atom": -0.09280315784533985,
                        "ncells": 2
                    },
                    {
                        "alat": 5.253612060546875,
                        "energy_total": -2.9697011199521723,
                        "energy_per_atom": -0.09280315999850539,
                        "ncells": 2
                    }
                ]
            }
        ],
        "selected_attempt_index": 0,
        "search_strategy": "coarse_scan_plus_nelder_mead_no_led",
        "all_alats": [
            5.3,
            5.565,
            5.034999999999999,
            5.167499999999999,
            5.432500000000001,
            5.233749999999999,
            5.167499999999998,
            5.266874999999999,
            5.299999999999999,
            5.250312499999999,
            5.233749999999999,
            5.258593749999999,
            5.242031249999998,
            5.2544531249999995,
            5.25859375,
            5.252382812499999,
            5.2565234375,
            5.253417968749999,
            5.252382812499999,
            5.253935546874999,
            5.252900390624999,
            5.253676757812499,
            5.253935546875,
            5.25354736328125,
            5.25341796875,
            5.253612060546875
        ],
        "all_energies_per_atom": [
            -0.09256933736191274,
            -0.08488093545774436,
            -0.0859553044527696,
            -0.09187270613426775,
            -0.0897953266766011,
            -0.09275736260313851,
            -0.09187270613426775,
            -0.0927832333125587,
            -0.09256933736191274,
            -0.09280194965265116,
            -0.09275736260313851,
            -0.09280028865430547,
            -0.09278778712410697,
            -0.09280307005496462,
            -0.09280028865430495,
            -0.09280300093650679,
            -0.09280216373165287,
            -0.09280315784533985,
            -0.09280300093650679,
            -0.09280314448504384,
            -0.0928031100308711,
            -0.0928031588054714,
            -0.09280314448504377,
            -0.09280316023629706,
            -0.09280315784533985,
            -0.09280315999850539
        ]
    },
    "equilibrium_alat": 5.25354736328125,
    "results": [
        {
            "ok": true,
            "status": "success",
            "configuration_type": "mono_species_fcc",
            "species_list": [
                "Ar"
            ],
            "species_label": "Ar",
            "good_alat": 5.25354736328125,
            "good_energy_per_atom": -0.09280316023629706,
            "good_energy_total": -2.969701127561506,
            "good_ncells": 2,
            "bounds": {
                "a_min": 1.5,
                "a_max": 12.0,
                "min_scan_alat_for_plateau": 6.5,
                "coarse_del_a": 0.1
            },
            "coarse_scan": {
                "alats": [
                    1.5,
                    1.6,
                    1.7,
                    1.8,
                    1.9,
                    2.0,
                    2.1,
                    2.2,
                    2.3,
                    2.4,
                    2.5,
                    2.6,
                    2.7,
                    2.8,
                    2.9,
                    3.0,
                    3.1,
                    3.2,
                    3.3,
                    3.4,
                    3.5,
                    3.6,
                    3.7,
                    3.8,
                    3.9,
                    4.0,
                    4.1,
                    4.2,
                    4.3,
                    4.4,
                    4.5,
                    4.6,
                    4.7,
                    4.8,
                    4.9,
                    5.0,
                    5.1,
                    5.2,
                    5.3,
                    5.4,
                    5.5,
                    5.6,
                    5.7,
                    5.8,
                    5.9,
                    6.0,
                    6.1,
                    6.2,
                    6.3,
                    6.4,
                    6.5,
                    6.6,
                    6.7,
                    6.8,
                    6.9,
                    7.0,
                    7.1,
                    7.2,
                    7.3,
                    7.4,
                    7.5,
                    7.6,
                    7.7,
                    7.8,
                    7.9,
                    8.0,
                    8.1,
                    8.2,
                    8.3,
                    8.4,
                    8.5,
                    8.6,
                    8.7,
                    8.8,
                    8.9,
                    9.0,
                    9.1,
                    9.2,
                    9.3,
                    9.4,
                    9.5,
                    9.6,
                    9.7,
                    9.8,
                    9.9,
                    10.0,
                    10.1,
                    10.2,
                    10.3,
                    10.4,
                    10.5,
                    10.6,
                    10.7,
                    10.8,
                    10.9,
                    11.0,
                    11.1,
                    11.2,
                    11.3,
                    11.4,
                    11.5,
                    11.6,
                    11.7,
                    11.8,
                    11.9,
                    12.0
                ],
                "energies_per_atom": [
                    486.02979831615653,
                    371.22981506033545,
                    285.38133818505656,
                    220.53624252045756,
                    171.146265059054,
                    133.26571038592016,
                    104.04441195508718,
                    81.39521429458102,
                    63.76997242457455,
                    50.00977295031356,
                    39.238949544009714,
                    30.79030496677257,
                    24.1523055441361,
                    18.930646207204543,
                    14.819749811905554,
                    11.581975487689958,
                    9.031485374247053,
                    7.0229670750666475,
                    5.441765572430094,
                    4.198301303842928,
                    3.2216739712894706,
                    2.4558517257972587,
                    1.8565874073571873,
                    1.3888777033859332,
                    1.024936835718084,
                    0.7428561671911494,
                    0.5252941950509864,
                    0.3584469655877889,
                    0.2314149529719729,
                    0.13546227502030175,
                    0.06376347358978095,
                    0.011036708771188671,
                    -0.026992435425755388,
                    -0.053720529326029734,
                    -0.07176326264641399,
                    -0.08319999800039436,
                    -0.08966015124771497,
                    -0.09245564037796285,
                    -0.09256933736191274,
                    -0.09071725890642389,
                    -0.08749280092229128,
                    -0.08335017168105638,
                    -0.07863432299602059,
                    -0.07361951006534993,
                    -0.06850324958675735,
                    -0.06339989790795537,
                    -0.058411427673759106,
                    -0.053608653774456866,
                    -0.04903856197188737,
                    -0.04473006164229408,
                    -0.040698488751617024,
                    -0.03694911882305597,
                    -0.03351138040706904,
                    -0.03037533444127543,
                    -0.027490903537183756,
                    -0.024846649118529407,
                    -0.022429407842940573,
                    -0.02022504757014277,
                    -0.018219030678499403,
                    -0.016396827312415353,
                    -0.01474421225559142,
                    -0.013247472044387922,
                    -0.01189354329879216,
                    -0.0106700987653731,
                    -0.009565594004804888,
                    -0.008569284830183124,
                    -0.0076712233627484385,
                    -0.0068693239393092425,
                    -0.0061536235477273864,
                    -0.005509056777468575,
                    -0.004928838052236602,
                    -0.0044067709593905435,
                    -0.003937209472568864,
                    -0.003515018830914989,
                    -0.0031355369655176727,
                    -0.0027945371036780502,
                    -0.002488191981465603,
                    -0.0022130399420625894,
                    -0.001965953081542495,
                    -0.0017441075169675733,
                    -0.001544955787653262,
                    -0.001366201354085604,
                    -0.001205775126293219,
                    -0.0010618139313097275,
                    -0.0009326408152271075,
                    -0.0008167470672774245,
                    -0.0007127758498572103,
                    -0.0006195073182283224,
                    -0.0005358451158604617,
                    -0.0004608041353049579,
                    -0.0003934994395536465,
                    -0.00033313624461951024,
                    -0.00027900087025886747,
                    -0.00023045257210075698,
                    -0.0001869161747836586,
                    -0.0001478754318968811,
                    -0.00011286704449678575,
                    -8.147527565755665e-05,
                    -5.332710388617035e-05,
                    -2.8087863261879512e-05,
                    -5.457322844342086e-06,
                    0.0,
                    0.0,
                    0.0,
                    0.0,
                    0.0
                ],
                "energy_total": [
                    15552.953546117009,
                    11879.354081930735,
                    9132.20282192181,
                    7057.159760654642,
                    5476.680481889728,
                    4264.502732349445,
                    3329.42118256279,
                    2604.6468574265928,
                    2040.6391175863855,
                    1600.312734410034,
                    1255.6463854083108,
                    985.2897589367223,
                    772.8737774123553,
                    605.7806786305454,
                    474.23199398097773,
                    370.62321560607865,
                    289.0075319759057,
                    224.73494640213272,
                    174.136498317763,
                    134.3456417229737,
                    103.09356708126306,
                    78.58725522551228,
                    59.410797035429994,
                    44.44408650834986,
                    32.797978742978685,
                    23.771397350116782,
                    16.809414241631565,
                    11.470302898809244,
                    7.405278495103133,
                    4.334792800649656,
                    2.0404311548729903,
                    0.3531746806780375,
                    -0.8637579336241724,
                    -1.7190569384329515,
                    -2.2964244046852476,
                    -2.6623999360126196,
                    -2.869124839926879,
                    -2.958580492094811,
                    -2.9622187955812076,
                    -2.9029522850055645,
                    -2.799769629513321,
                    -2.667205493793804,
                    -2.516298335872659,
                    -2.355824322091198,
                    -2.1921039867762353,
                    -2.028796733054572,
                    -1.8691656855602914,
                    -1.7154769207826197,
                    -1.5692339831003959,
                    -1.4313619725534106,
                    -1.3023516400517448,
                    -1.182371802337791,
                    -1.0723641730262092,
                    -0.9720107021208138,
                    -0.8797089131898802,
                    -0.795092771792941,
                    -0.7177410509740983,
                    -0.6472015222445686,
                    -0.5830089817119809,
                    -0.5246984739972913,
                    -0.4718147921789254,
                    -0.4239191054204135,
                    -0.38059338556134914,
                    -0.3414431604919392,
                    -0.3060990081537564,
                    -0.27421711456585995,
                    -0.24547914760795003,
                    -0.21981836605789576,
                    -0.19691595352727637,
                    -0.1762898168789944,
                    -0.15772281767157126,
                    -0.1410166707004974,
                    -0.12599070312220365,
                    -0.11248060258927965,
                    -0.10033718289656553,
                    -0.08942518731769761,
                    -0.0796221434068993,
                    -0.07081727814600286,
                    -0.06291049860935984,
                    -0.055811440542962346,
                    -0.049438585204904385,
                    -0.04371844333073933,
                    -0.03858480404138301,
                    -0.03397804580191128,
                    -0.02984450608726744,
                    -0.026135906152877583,
                    -0.02280882719543073,
                    -0.019824234183306318,
                    -0.017147043707534775,
                    -0.014745732329758654,
                    -0.012591982065716689,
                    -0.010660359827824328,
                    -0.008928027848283759,
                    -0.007374482307224223,
                    -0.005981317593077075,
                    -0.0047320138207001955,
                    -0.003611745423897144,
                    -0.002607208821041813,
                    -0.0017064673243574512,
                    -0.0008988116243801444,
                    -0.00017463433101894675,
                    0.0,
                    0.0,
                    0.0,
                    0.0,
                    0.0
                ],
                "ncells": [
                    2,
                    2,
                    2,
                    2,
                    2,
                    2,
                    2,
                    2,
                    2,
                    2,
                    2,
                    2,
                    2,
                    2,
                    2,
                    2,
                    2,
                    2,
                    2,
                    2,
                    2,
                    2,
                    2,
                    2,
                    2,
                    2,
                    2,
                    2,
                    2,
                    2,
                    2,
                    2,
                    2,
                    2,
                    2,
                    2,
                    2,
                    2,
                    2,
                    2,
                    2,
                    2,
                    2,
                    2,
                    2,
                    2,
                    2,
                    2,
                    2,
                    2,
                    2,
                    2,
                    2,
                    2,
                    2,
                    2,
                    2,
                    2,
                    2,
                    2,
                    2,
                    2,
                    2,
                    2,
                    2,
                    2,
                    2,
                    2,
                    2,
                    2,
                    2,
                    2,
                    2,
                    2,
                    2,
                    2,
                    2,
                    2,
                    2,
                    2,
                    2,
                    2,
                    2,
                    2,
                    2,
                    2,
                    2,
                    2,
                    2,
                    2,
                    2,
                    2,
                    2,
                    2,
                    2,
                    2,
                    2,
                    2,
                    2,
                    2,
                    2,
                    2,
                    2,
                    2,
                    2,
                    2
                ],
                "a_min": 1.5,
                "a_max": 12.0,
                "del_a": 0.1,
                "initial_use_safe": true,
                "safe_successes_before_direct": 10,
                "switched_to_direct": true,
                "switch_alat": 2.4,
                "early_stop_plateau": true,
                "plateau_stop_alat": null
            },
            "coarse_minima": [
                {
                    "index": 38,
                    "alat": 5.3,
                    "energy_per_atom": -0.09256933736191274
                }
            ],
            "nelder_mead_attempts": [
                {
                    "ok": true,
                    "status": "success",
                    "message": "Optimization terminated successfully.",
                    "start_alat": 5.3,
                    "good_alat": 5.25354736328125,
                    "good_energy_total": -2.969701127561506,
                    "good_energy_per_atom": -0.09280316023629706,
                    "good_ncells": 2,
                    "optimizer_x": 5.25354736328125,
                    "optimizer_fun": -0.09280316023629706,
                    "nfev": 26,
                    "nit": 13,
                    "evaluations": [
                        {
                            "alat": 5.3,
                            "energy_total": -2.9622187955812076,
                            "energy_per_atom": -0.09256933736191274,
                            "ncells": 2
                        },
                        {
                            "alat": 5.565,
                            "energy_total": -2.7161899346478195,
                            "energy_per_atom": -0.08488093545774436,
                            "ncells": 2
                        },
                        {
                            "alat": 5.034999999999999,
                            "energy_total": -2.750569742488627,
                            "energy_per_atom": -0.0859553044527696,
                            "ncells": 2
                        },
                        {
                            "alat": 5.167499999999999,
                            "energy_total": -2.939926596296568,
                            "energy_per_atom": -0.09187270613426775,
                            "ncells": 2
                        },
                        {
                            "alat": 5.432500000000001,
                            "energy_total": -2.8734504536512353,
                            "energy_per_atom": -0.0897953266766011,
                            "ncells": 2
                        },
                        {
                            "alat": 5.233749999999999,
                            "energy_total": -2.9682356033004322,
                            "energy_per_atom": -0.09275736260313851,
                            "ncells": 2
                        },
                        {
                            "alat": 5.167499999999998,
                            "energy_total": -2.939926596296568,
                            "energy_per_atom": -0.09187270613426775,
                            "ncells": 2
                        },
                        {
                            "alat": 5.266874999999999,
                            "energy_total": -2.969063466001878,
                            "energy_per_atom": -0.0927832333125587,
                            "ncells": 2
                        },
                        {
                            "alat": 5.299999999999999,
                            "energy_total": -2.9622187955812076,
                            "energy_per_atom": -0.09256933736191274,
                            "ncells": 2
                        },
                        {
                            "alat": 5.250312499999999,
                            "energy_total": -2.9696623888848372,
                            "energy_per_atom": -0.09280194965265116,
                            "ncells": 2
                        },
                        {
                            "alat": 5.233749999999999,
                            "energy_total": -2.9682356033004322,
                            "energy_per_atom": -0.09275736260313851,
                            "ncells": 2
                        },
                        {
                            "alat": 5.258593749999999,
                            "energy_total": -2.969609236937775,
                            "energy_per_atom": -0.09280028865430547,
                            "ncells": 2
                        },
                        {
                            "alat": 5.242031249999998,
                            "energy_total": -2.969209187971423,
                            "energy_per_atom": -0.09278778712410697,
                            "ncells": 2
                        },
                        {
                            "alat": 5.2544531249999995,
                            "energy_total": -2.9696982417588678,
                            "energy_per_atom": -0.09280307005496462,
                            "ncells": 2
                        },
                        {
                            "alat": 5.25859375,
                            "energy_total": -2.9696092369377585,
                            "energy_per_atom": -0.09280028865430495,
                            "ncells": 2
                        },
                        {
                            "alat": 5.252382812499999,
                            "energy_total": -2.969696029968217,
                            "energy_per_atom": -0.09280300093650679,
                            "ncells": 2
                        },
                        {
                            "alat": 5.2565234375,
                            "energy_total": -2.969669239412892,
                            "energy_per_atom": -0.09280216373165287,
                            "ncells": 2
                        },
                        {
                            "alat": 5.253417968749999,
                            "energy_total": -2.9697010510508752,
                            "energy_per_atom": -0.09280315784533985,
                            "ncells": 2
                        },
                        {
                            "alat": 5.252382812499999,
                            "energy_total": -2.969696029968217,
                            "energy_per_atom": -0.09280300093650679,
                            "ncells": 2
                        },
                        {
                            "alat": 5.253935546874999,
                            "energy_total": -2.969700623521403,
                            "energy_per_atom": -0.09280314448504384,
                            "ncells": 2
                        },
                        {
                            "alat": 5.252900390624999,
                            "energy_total": -2.9696995209878754,
                            "energy_per_atom": -0.0928031100308711,
                            "ncells": 2
                        },
                        {
                            "alat": 5.253676757812499,
                            "energy_total": -2.9697010817750846,
                            "energy_per_atom": -0.0928031588054714,
                            "ncells": 2
                        },
                        {
                            "alat": 5.253935546875,
                            "energy_total": -2.9697006235214007,
                            "energy_per_atom": -0.09280314448504377,
                            "ncells": 2
                        },
                        {
                            "alat": 5.25354736328125,
                            "energy_total": -2.969701127561506,
                            "energy_per_atom": -0.09280316023629706,
                            "ncells": 2
                        },
                        {
                            "alat": 5.25341796875,
                            "energy_total": -2.9697010510508752,
                            "energy_per_atom": -0.09280315784533985,
                            "ncells": 2
                        },
                        {
                            "alat": 5.253612060546875,
                            "energy_total": -2.9697011199521723,
                            "energy_per_atom": -0.09280315999850539,
                            "ncells": 2
                        }
                    ]
                }
            ],
            "selected_attempt_index": 0,
            "search_strategy": "coarse_scan_plus_nelder_mead_no_led",
            "all_alats": [
                5.3,
                5.565,
                5.034999999999999,
                5.167499999999999,
                5.432500000000001,
                5.233749999999999,
                5.167499999999998,
                5.266874999999999,
                5.299999999999999,
                5.250312499999999,
                5.233749999999999,
                5.258593749999999,
                5.242031249999998,
                5.2544531249999995,
                5.25859375,
                5.252382812499999,
                5.2565234375,
                5.253417968749999,
                5.252382812499999,
                5.253935546874999,
                5.252900390624999,
                5.253676757812499,
                5.253935546875,
                5.25354736328125,
                5.25341796875,
                5.253612060546875
            ],
            "all_energies_per_atom": [
                -0.09256933736191274,
                -0.08488093545774436,
                -0.0859553044527696,
                -0.09187270613426775,
                -0.0897953266766011,
                -0.09275736260313851,
                -0.09187270613426775,
                -0.0927832333125587,
                -0.09256933736191274,
                -0.09280194965265116,
                -0.09275736260313851,
                -0.09280028865430547,
                -0.09278778712410697,
                -0.09280307005496462,
                -0.09280028865430495,
                -0.09280300093650679,
                -0.09280216373165287,
                -0.09280315784533985,
                -0.09280300093650679,
                -0.09280314448504384,
                -0.0928031100308711,
                -0.0928031588054714,
                -0.09280314448504377,
                -0.09280316023629706,
                -0.09280315784533985,
                -0.09280315999850539
            ]
        }
    ],
    "model_shortname": "Morse_Jelinek"
}